{
  "ayahs": {
    "1": "Ar-Raḥmān",
    "2": "‘Allama l-Qur’ān",
    "3": "Khalaqa l-insān",
    "4": "‘Allamahul-bayān",
    "5": "Ash-shamsu wal-qamaru biḥusbān",
    "6": "Wan-najmu wash-shajaru yasjudān",
    "7": "Was-samā’a rafa‘ahā wa waḍa‘al-mīzān",
    "8": "Allā taṭghaw fil-mīzān",
    "9": "Wa aqīmūl-wazna bil-qiṣṭi wa lā tukh’sirūl-mīzān",
    "10": "Wal-arḍa waḍa‘ahā lil-anām",
    "11": "Fīhā fākihatun wan-nakhlu dhātu l-akmām",
    "12": "Wal-ḥabbu dhūl-‘aṣfi war-rayḥān",
    "13": "Fa-bi’ayyi ālā’i rabbikumā tukaḏḏibān",
    "14": "Khalaqal-insāna min ṣalṣālin kal-fakhkhār",
    "15": "Wa khalaqal-jāna min mārijin min nār",
    "16": "Fa-bi’ayyi ālā’i rabbikumā tukaḏḏibān",
    "17": "Rabbu l-mashriqayni wa rabbu l-maghribayn",
    "18": "Fa-bi’ayyi ālā’i rabbikumā tukaḏḏibān",
    "19": "Marajal-baḥrayni yaltaqiyān",
    "20": "Baynahumā barzakhun lā yabghiyān",
    "21": "Fa-bi’ayyi ālā’i rabbikumā tukaḏḏibān",
    "22": "Yakhruju minhumā l-lu’lu’u wal-marjān",
    "23": "Fa-bi’ayyi ālā’i rabbikumā tukaḏḏibān",
    "24": "Walahul-jawāri l-munsha’ātu fil-baḥri kal-a‘lām",
    "25": "Fa-bi’ayyi ālā’i rabbikumā tukaḏḏibān",
    "26": "Kullu man ‘alayhā fān",
    "27": "Wa yabqā wajhu rabbika dhu l-jalāli wal-ikrām",
    "28": "Fa-bi’ayyi ālā’i rabbikumā tukaḏḏibān",
    "29": "Yas’aluhu man fis-samāwāti wal-arḍ, kulla yawmin huwa fī sha’n",
    "30": "Fa-bi’ayyi ālā’i rabbikumā tukaḏḏibān",
    "31": "Sanafrughu lakum ayyuhath-thaqalān",
    "32": "Fa-bi’ayyi ālā’i rabbikumā tukaḏḏibān",
    "33": "Yā ma‘shara l-jinni wal-insi inis-taṭa‘tum an tanfudhū min aqṭāri s-samāwāti wal-arḍi fanfudhū, lā tanfudhūna illā bisulṭān",
    "34": "Fa-bi’ayyi ālā’i rabbikumā tukaḏḏibān",
    "35": "Yursalu ‘alaykumā shuwāẓun min nārin wa nuḥāsun falā tantaṣirān",
    "36": "Fa-bi’ayyi ālā’i rabbikumā tukaḏḏibān",
    "37": "Fa-idhanshaqqat is-samā’u fakānat wardatan kaddi-hān",
    "38": "Fa-bi’ayyi ālā’i rabbikumā tukaḏḏibān",
    "39": "Fayawma’idhin lā yus’alu ‘an dhanbihi insun walā jān",
    "40": "Fa-bi’ayyi ālā’i rabbikumā tukaḏḏibān",
    "41": "Yu‘rafu l-mujrimūna bisīmāhum fayu’khadhu bin-nawāṣī wal-aqdām",
    "42": "Fa-bi’ayyi ālā’i rabbikumā tukaḏḏibān",
    "43": "Hādhihi jahannamullatī yukadhdhibu bihā l-mujrimūn",
    "44": "Yaṭūfūna baynahā wa bayna ḥamīmin ān",
    "45": "Fa-bi’ayyi ālā’i rabbikumā tukaḏḏibān",
    "46": "Waliman khāfa maqāma rabbihi jannatān",
    "47": "Fa-bi’ayyi ālā’i rabbikumā tukaḏḏibān",
    "48": "Dhātā afnān",
    "49": "Fa-bi’ayyi ālā’i rabbikumā tukaḏḏibān",
    "50": "Fīhimā ‘aynāni tajriān",
    "51": "Fa-bi’ayyi ālā’i rabbikumā tukaḏḏibān",
    "52": "Fīhimā min kulli fākihatin zawjān",
    "53": "Fa-bi’ayyi ālā’i rabbikumā tukaḏḏibān",
    "54": "Mut-taki’īna ‘alā furushin baṭā’inu-hā min istabraq, wa janā l-jannatayni dān",
    "55": "Fa-bi’ayyi ālā’i rabbikumā tukaḏḏibān",
    "56": "Fīhinna qāṣirātu ṭ-ṭarfi lam yaṭmithhunna insun qabla-hum walā jān",
    "57": "Fa-bi’ayyi ālā’i rabbikumā tukaḏḏibān",
    "58": "Ka’annahunna l-yaqūtu wal-marjān",
    "59": "Fa-bi’ayyi ālā’i rabbikumā tukaḏḏibān",
    "60": "Hal jazā’u l-iḥsāni illā l-iḥsān",
    "61": "Fa-bi’ayyi ālā’i rabbikumā tukaḏḏibān",
    "62": "Wa min dūnihimā jannatān",
    "63": "Fa-bi’ayyi ālā’i rabbikumā tukaḏḏibān",
    "64": "Mud-hāmmatān",
    "65": "Fa-bi’ayyi ālā’i rabbikumā tukaḏḏibān",
    "66": "Fīhimā ‘aynāni nāḍikhātān",
    "67": "Fa-bi’ayyi ālā’i rabbikumā tukaḏḏibān",
    "68": "Fīhimā fākihatun wa nakhlun wa rummān",
    "69": "Fa-bi’ayyi ālā’i rabbikumā tukaḏḏibān",
    "70": "Fīhinna khayrātun ḥisān",
    "71": "Fa-bi’ayyi ālā’i rabbikumā tukaḏḏibān",
    "72": "Ḥūr maqṣūrātun fil-khiyām",
    "73": "Fa-bi’ayyi ālā’i rabbikumā tukaḏḏibān",
    "74": "Lam yaṭmithhunna insun qabla-hum walā jān",
    "75": "Fa-bi’ayyi ālā’i rabbikumā tukaḏḏibān",
    "76": "Mut-taki’īna ‘alā rafrafin khuḍrin wa ‘abqariyyin ḥisān",
    "77": "Fa-bi’ayyi ālā’i rabbikumā tukaḏḏibān",
    "78": "Tabāraka smu rabbika dhī l-jalāli wal-ikrām"
  }
}
